tdl/__init__.py
tdl/audit/__init__.py
tdl/audit/presentation_utils.py
tdl/audit/stdout_audit_stream.py
tdl/queue/__init__.py
tdl/queue/implementation_runner_config.py
tdl/queue/processing_rules.py
tdl/queue/queue_based_implementation_runner.py
tdl/queue/abstractions/__init__.py
tdl/queue/abstractions/processing_rule.py
tdl/queue/abstractions/request.py
tdl/queue/abstractions/response/__init__.py
tdl/queue/abstractions/response/fatal_error_response.py
tdl/queue/abstractions/response/valid_response.py
tdl/queue/transport/__init__.py
tdl/queue/transport/listener.py
tdl/queue/transport/remote_broker.py
tdl/runner/__init__.py
tdl/runner/challenge_server_client.py
tdl/runner/challenge_session.py
tdl/runner/challenge_session_config.py
tdl/runner/recording_system.py
tdl/runner/round_management.py
tdl/runner/runner_action.py
tdl_client_python-0.30.1.dist-info/licenses/LICENSE
tdl_client_python-0.30.1.dist-info/METADATA
tdl_client_python-0.30.1.dist-info/WHEEL
tdl_client_python-0.30.1.dist-info/top_level.txt
tdl_client_python-0.30.1.dist-info/RECORD
