Metadata-Version: 2.4
Name: tdl-client-python
Version: 0.30.1
Summary: tdl-client-python
Home-page: https://github.com/julianghionoiu/tdl-client-python
Download-URL: https://github.com/julianghionoiu/tdl-client-python/archive/v0.30.1.tar.gz
Author: Julian Ghionoiu
Author-email: julian.ghionoiu@gmail.com
Keywords: kata,activemq,rpc
License-File: LICENSE
Requires-Dist: stomp.py==8.2.0
Requires-Dist: requests==2.32.3
Dynamic: author
Dynamic: author-email
Dynamic: description
Dynamic: description-content-type
Dynamic: download-url
Dynamic: home-page
Dynamic: keywords
Dynamic: license-file
Dynamic: requires-dist
Dynamic: summary
